pkg22/__init__.py
pkg22/__main__.py
pkg22/demo1.py
pkg22/demo2.py
test/__init__.py
test/__main__.py
test/demo1.py
test/demo2.py
test22/__init__.py
test22/__main__.py
test22/demo1.py
test22/demo2.py
pkg22-1.0.0.dist-info/METADATA
pkg22-1.0.0.dist-info/WHEEL
pkg22-1.0.0.dist-info/top_level.txt
pkg22-1.0.0.dist-info/RECORD
