Metadata-Version: 2.1
Name: pkg22
Version: 1.0.0
Summary: A print test for PyPI
Home-page: https://www.python.org/
Author: hao.liu
Author-email: win@163.com
License: MIT
Project-URL: Documentation, https://packaging.python.org/tutorials/distributing-packages/
Project-URL: Funding, https://donate.pypi.org
Project-URL: Source, https://github.com/pypa/sampleproject/
Project-URL: Tracker, https://github.com/pypa/sampleproject/issues
Keywords: ga nn
Platform: UNKNOWN
Requires-Python: >=3
